{
  "store": "sk",
  "country": "Slovakia",
  "locales": [
    "sk",
    "cs",
    "en-US"
  ],
  "keywordCount": 43,
  "keywords": [
    "chrbát",
    "sediaci",
    "ergonómia",
    "airpods",
    "hodinky",
    "widget",
    "návyk",
    "páteř",
    "ramená",
    "kancelária",
    "homeoffice",
    "kamera",
    "posture check",
    "aktívne",
    "posture check – aktívne",
    "check aktívne",
    "krk, stôl a držanie tela",
    "krk stôl",
    "držanie tela",
    "záda",
    "sedící",
    "ergonomie",
    "ramena",
    "kancelář",
    "kalibrace",
    "aktivně",
    "posture check – aktivně",
    "check aktivně",
    "krk, stůl a držení těla",
    "krk stůl",
    "držení těla",
    "back",
    "spine",
    "alignment",
    "habit",
    "watch",
    "ergonomics",
    "sit",
    "shoulders",
    "office",
    "wfh",
    "camera",
    "active daily",
    "posture check - active daily",
    "check active"
  ]
}
